[
  {
    "outputFileName": "wwwroot/css/official.min.css",
    "inputFiles": [
      "wwwroot/css/official.css"
    ]
  },
  {
    "outputFileName": "wwwroot/css/platform.min.css",
    "inputFiles": [
      "wwwroot/css/platform.css"
    ]
  },
  {
    "outputFileName": "wwwroot/js/platform.min.js",
    "inputFiles": [
      "wwwroot/js/platform.js",
      "wwwroot/js/districts.js",
      "wwwroot/js/jobClasses.js",
      "wwwroot/js/worker.js",
      "wwwroot/js/order.js",
      "wwwroot/js/organize.js",
      "wwwroot/js/workLoads.js"
    ],
    "minify": {
      "enabled": true,
      "renameLocals": true
    }
  },
  {
    "outputFileName": "wwwroot/js/official.min.js",
    "inputFiles": [
      "wwwroot/js/official.js"
    ],
    "minify": {
      "enabled": true,
      "renameLocals": true
    }
  },
  {
    "outputFileName": "wwwroot/js/amap.min.js",
    "inputFiles": [
      "wwwroot/js/amap.js"
    ],
    "minify": {
      "enabled": true,
      "renameLocals": true
    }
  },
  {
    "outputFileName": "wwwroot/js/crop.min.js",
    "inputFiles": [
      "wwwroot/js/crop.js"
    ],
    "minify": {
      "enabled": true,
      "renameLocals": true
    }
  },
  {
    "outputFileName": "wwwroot/js/base64.min.js",
    "inputFiles": [
      "wwwroot/js/base64.js"
    ]
  }
]
